pdf_processor/__init__.py
pdf_processor/processor.py
rainbow_pdf_processor-0.1.0.dist-info/licenses/LICENSE
rainbow_pdf_processor-0.1.0.dist-info/METADATA
rainbow_pdf_processor-0.1.0.dist-info/WHEEL
rainbow_pdf_processor-0.1.0.dist-info/top_level.txt
rainbow_pdf_processor-0.1.0.dist-info/RECORD
