Metadata-Version: 2.4
Name: rainbow-pdf-processor
Version: 0.1.0
Summary: A powerful PDF processing tool with text extraction, table recognition, and image extraction capabilities
Author-email: zhanghanlin <zhanghanlin@163.com>
License: MIT
Project-URL: Homepage, https://github.com/RainbowGuysForFun/pdf-processor
Project-URL: Bug Tracker, https://github.com/RainbowGuysForFun/pdf-processor/issues
Project-URL: Documentation, https://github.com/RainbowGuysForFun/pdf-processor#readme
Project-URL: Source Code, https://github.com/RainbowGuysForFun/pdf-processor
Keywords: pdf,text extraction,table recognition,image extraction,document processing
Classifier: Development Status :: 4 - Beta
Classifier: Intended Audience :: Developers
Classifier: Topic :: Software Development :: Libraries :: Python Modules
Classifier: Topic :: Text Processing :: General
Classifier: Programming Language :: Python :: 3
Classifier: Programming Language :: Python :: 3.8
Classifier: Programming Language :: Python :: 3.9
Classifier: Programming Language :: Python :: 3.10
Classifier: Programming Language :: Python :: 3.11
Classifier: Programming Language :: Python :: 3.12
Classifier: Programming Language :: Python :: 3.13
Classifier: License :: OSI Approved :: MIT License
Classifier: Operating System :: OS Independent
Requires-Python: >=3.8
License-File: LICENSE
Requires-Dist: PyMuPDF>=1.25.0
Provides-Extra: dev
Requires-Dist: PyMuPDF>=1.25.0; extra == "dev"
Requires-Dist: black; extra == "dev"
Requires-Dist: isort; extra == "dev"
Requires-Dist: flake8; extra == "dev"
Requires-Dist: mypy; extra == "dev"
Provides-Extra: test
Requires-Dist: PyMuPDF>=1.25.0; extra == "test"
Requires-Dist: pytest; extra == "test"
Requires-Dist: pytest-cov; extra == "test"
Requires-Dist: pytest-mock; extra == "test"
Requires-Dist: pytest-asyncio; extra == "test"
Dynamic: license-file
